deskpets/__init__.py
deskpets/config.json
deskpets/credits.py
deskpets/logo.ico
deskpets/main.py
deskpets/pets.py
deskpets/pets_data.json
deskpets/pets_list.json
deskpets/petworker.py
deskpets/remove_alpha.py
deskpets/selector.py
deskpets/settings.py
deskpets/size.py
deskpets/squirrel_climb.py
deskpets/state.py
deskpets/window.py
deskpets/windows_API.py
deskpets/media/README.md
deskpets/media/animals.svg
deskpets/media/cat.svg
deskpets/media/dog.svg
deskpets/media/extra.zip
deskpets/media/extraIcons.zip
deskpets/media/pet-grid.png
deskpets/media/backgrounds/autumn/background-dark-large.png
deskpets/media/backgrounds/autumn/background-dark-medium.png
deskpets/media/backgrounds/autumn/background-dark-nano.png
deskpets/media/backgrounds/autumn/background-dark-small.png
deskpets/media/backgrounds/autumn/background-light-large.png
deskpets/media/backgrounds/autumn/background-light-medium.png
deskpets/media/backgrounds/autumn/background-light-nano.png
deskpets/media/backgrounds/autumn/background-light-small.png
deskpets/media/backgrounds/autumn/background.png
deskpets/media/backgrounds/autumn/foreground-dark-large.png
deskpets/media/backgrounds/autumn/foreground-dark-medium.png
deskpets/media/backgrounds/autumn/foreground-dark-nano.png
deskpets/media/backgrounds/autumn/foreground-dark-small.png
deskpets/media/backgrounds/autumn/foreground-light-large.png
deskpets/media/backgrounds/autumn/foreground-light-medium.png
deskpets/media/backgrounds/autumn/foreground-light-nano.png
deskpets/media/backgrounds/autumn/foreground-light-small.png
deskpets/media/backgrounds/beach/background-dark-large.png
deskpets/media/backgrounds/beach/background-dark-medium.png
deskpets/media/backgrounds/beach/background-dark-nano.png
deskpets/media/backgrounds/beach/background-dark-small.png
deskpets/media/backgrounds/beach/background-dark.png
deskpets/media/backgrounds/beach/background-light-large.png
deskpets/media/backgrounds/beach/background-light-medium.png
deskpets-1.2.0.dist-info/licenses/LICENSE
deskpets-1.2.0.dist-info/METADATA
deskpets-1.2.0.dist-info/WHEEL
deskpets-1.2.0.dist-info/entry_points.txt
deskpets-1.2.0.dist-info/top_level.txt
deskpets-1.2.0.dist-info/RECORD
