Metadata-Version: 2.4
Name: deskpets
Version: 1.2.0
Summary: Desktop pixel pets for Windows
Author: Minniti Julien
License: MIT License
Project-URL: Homepage, https://github.com/Jumitti/DeskPets
Requires-Python: >=3.10
License-File: LICENSE
Requires-Dist: PyQt6
Requires-Dist: PyQt6-WebEngine
Requires-Dist: Pillow
Requires-Dist: pywin32
Dynamic: license-file
